pyvms/ConfigSocket.py
pyvms/Crc32.py
pyvms/DbMySql.py
pyvms/Discovery.py
pyvms/Protocol.py
pyvms/Regs.py
pyvms/TimeSocket.py
pyvms/TimeStats.py
pyvms/__init__.py
pyvms-0.1.4.dist-info/LICENSE
pyvms-0.1.4.dist-info/METADATA
pyvms-0.1.4.dist-info/WHEEL
pyvms-0.1.4.dist-info/top_level.txt
pyvms-0.1.4.dist-info/RECORD
