Metadata-Version: 2.1
Name: pyvms
Version: 0.1.4
Summary: Python module for Vibration Monitoring System by Logic Elements
Author-email: Jan Bartovský <jan.bartovsky@logicelements.cz>
Project-URL: Homepage, https://github.com/LogicElements/py-vms
Keywords: logicelements,vibration,vms
Classifier: Programming Language :: Python :: 3
Classifier: License :: OSI Approved :: MIT License
Classifier: Operating System :: OS Independent
Requires-Python: >=3.7
License-File: LICENSE
Requires-Dist: pyserial
Requires-Dist: mysql-connector
Requires-Dist: unittest-xml-reporting
Provides-Extra: extra
Requires-Dist: matplotlib ; extra == 'extra'
